simple_azure_utils/__init__.py
simple_azure_utils/app_configuration.py
simple_azure_utils/azure_data_lake_storage.py
simple_azure_utils/service_principal.py
tests/__init__.py
tests/test_example.py
tests/test_helper.py
simple_azure_utils-0.1.14.dist-info/METADATA
simple_azure_utils-0.1.14.dist-info/WHEEL
simple_azure_utils-0.1.14.dist-info/top_level.txt
simple_azure_utils-0.1.14.dist-info/RECORD
