Metadata-Version: 2.1
Name: simple-azure-utils
Version: 0.1.14
Summary: A simple set of utilities for interacting with Azure
Home-page: UNKNOWN
Author: Terrell Mack
Author-email: terrell.mack@live.com
License: UNKNOWN
Keywords: python,azure
Platform: UNKNOWN
Classifier: Development Status :: 3 - Alpha
Classifier: Intended Audience :: Education
Classifier: Programming Language :: Python :: 3
Classifier: Operating System :: MacOS :: MacOS X
Classifier: Operating System :: Microsoft :: Windows
Requires-Dist: azure-storage-blob (>=12.14.0)
Requires-Dist: azure-identity (>=1.24.0)
Requires-Dist: azure-keyvault (==4.2.0)
Requires-Dist: azure-appconfiguration (==1.3.0)
Requires-Dist: azure-core (==1.35.0)
